examples/__init__.py
examples/image_processing_workflow.py
swafe/__init__.py
swafe/activity.py
swafe/cli.py
swafe/daemon.py
swafe/helpers.py
swafe/lib.py
swafe/poller.py
swafe/runner.py
swafe/task.py
swafe/workflow.py
swafe/exceptions/__init__.py
swafe/exceptions/activity_failed.py
swafe/exceptions/excecution_failed.py
swafe/exceptions/malformed_task.py
swafe/exceptions/workflow_failed.py
swafe/tests/__init__.py
swafe/tests/mocker.py
swafe/tests/test_cli.py
swafe/tests/test_poller.py
swafe-1.0.0.dist-info/DESCRIPTION.rst
swafe-1.0.0.dist-info/entry_points.txt
swafe-1.0.0.dist-info/METADATA
swafe-1.0.0.dist-info/metadata.json
swafe-1.0.0.dist-info/RECORD
swafe-1.0.0.dist-info/top_level.txt
swafe-1.0.0.dist-info/WHEEL
